sqlacodegen_v2/__init__.py
sqlacodegen_v2/__main__.py
sqlacodegen_v2/cli.py
sqlacodegen_v2/external.py
sqlacodegen_v2/generators.py
sqlacodegen_v2/models.py
sqlacodegen_v2/py.typed
sqlacodegen_v2/utils.py
sqlacodegen_v2-0.1.4.dist-info/LICENSE
sqlacodegen_v2-0.1.4.dist-info/METADATA
sqlacodegen_v2-0.1.4.dist-info/WHEEL
sqlacodegen_v2-0.1.4.dist-info/entry_points.txt
sqlacodegen_v2-0.1.4.dist-info/top_level.txt
sqlacodegen_v2-0.1.4.dist-info/RECORD
