Metadata-Version: 2.1
Name: sqlacodegen-v2
Version: 0.1.4
Summary: Automatic model code generator for SQLAlchemy 2.0
Author-email: Chengkai Mai <c.mai@madainchina.com>
License: MIT
Project-URL: Bug Tracker, https://github.com/maacck/sqlacodegen_v2/issues
Project-URL: Source Code, https://github.com/maacck/sqlacodegen_v2
Keywords: sqlalchemy
Classifier: Development Status :: 5 - Production/Stable
Classifier: Intended Audience :: Developers
Classifier: License :: OSI Approved :: MIT License
Classifier: Environment :: Console
Classifier: Topic :: Database
Classifier: Topic :: Software Development :: Code Generators
Classifier: Programming Language :: Python
Classifier: Programming Language :: Python :: 3
Classifier: Programming Language :: Python :: 3.7
Classifier: Programming Language :: Python :: 3.8
Classifier: Programming Language :: Python :: 3.9
Classifier: Programming Language :: Python :: 3.10
Requires-Python: >=3.7
Provides-Extra: test
Provides-Extra: citext
License-File: LICENSE
